{
  "products": [
		{
			"image": "bis",
			"title": "Bis Xtra 300g",
			"price": "3,49",
			"installment": 1
		},
		{
			"image": "kitkat",
			"title": "Kit kat ao leite 41,5g",
			"price": "6,00",
			"installment": 1
		},
		{
			"image": "lacta-branco",
			"title": "Chocolate Lacta Branco 90g",
			"price": "5,49",
			"installment": 1
		},
		{
			"image": "kitkat-branco",
			"title": "Kit kat branco 41,5g",
			"price": "5,99",
			"installment": 1
		},
		{
			"image": "xbox",
			"title": "Xbox Series S 500gb ssd",
			"price": "2.249,20",
			"installment": 4
		},
		{
			"title": "Ergonomic Concrete Computer",
			"price": "90.00",
			"installment": 1,
			"image": "bis",
			"id": "2b217b8c-d3e8-4ed6-b1b5-5bf8813829f9"
	},
	{
			"title": "Incredible Wooden Chips",
			"price": "19.00",
			"installment": 1,
			"image": "bis",
			"id": "f150b89a-119d-439f-b215-fb152d174fab"
	},
	{
			"title": "Refined Cotton Chicken",
			"price": "84.00",
			"installment": 1,
			"image": "bis",
			"id": "713c2498-577a-4a79-b72c-3967c2752991"
	},
	{
			"title": "Luxurious Soft Chicken",
			"price": "38.00",
			"installment": 1,
			"image": "bis",
			"id": "15d25276-331d-4d09-a687-7963d3ee0a28"
	},
	{
			"title": "Rustic Plastic Chair",
			"price": "100.00",
			"installment": 1,
			"image": "bis",
			"id": "2eaa61db-568e-4049-8991-26611540a839"
	},
	{
			"title": "Oriental Cotton Hat",
			"price": "31.00",
			"installment": 1,
			"image": "bis",
			"id": "1706c037-9d4c-4b91-86b5-248b4a76fc84"
	},
	{
			"title": "Incredible Bronze Bike",
			"price": "44.00",
			"installment": 1,
			"image": "bis",
			"id": "7721e4ad-4c63-4d9a-b298-1fe8d73e8aa9"
	},
	{
			"title": "Sleek Soft Bike",
			"price": "55.00",
			"installment": 1,
			"image": "bis",
			"id": "370aa156-0e9a-4002-a182-e15ee1616692"
	},
	{
			"title": "Rustic Concrete Bike",
			"price": "34.00",
			"installment": 1,
			"image": "bis",
			"id": "08da3030-2dc2-4487-a944-1025be7dbf78"
	},
	{
			"title": "Awesome Cotton Bacon",
			"price": "20.00",
			"installment": 1,
			"image": "bis",
			"id": "596db226-faea-4e04-99ef-722fa2ff6d74"
	},
	{
			"title": "Generic Plastic Computer",
			"price": "66.00",
			"installment": 1,
			"image": "bis",
			"id": "b37054c1-6ac7-4a8e-aef0-269f0fcfb559"
	},
	{
			"title": "Elegant Rubber Gloves",
			"price": "66.00",
			"installment": 1,
			"image": "bis",
			"id": "8cef27de-6300-4b94-b4a8-34ea9011ce17"
	},
	{
			"title": "Licensed Fresh Mouse",
			"price": "26.00",
			"installment": 1,
			"image": "bis",
			"id": "8021aae9-48bf-4891-a9fc-be2a0e847c14"
	},
	{
			"title": "Handcrafted Concrete Chicken",
			"price": "66.00",
			"installment": 1,
			"image": "bis",
			"id": "74ddda66-17fb-4ed0-9af2-caa0a4f3b484"
	},
	{
			"title": "Generic Steel Pizza",
			"price": "89.00",
			"installment": 1,
			"image": "bis",
			"id": "a4436059-2b42-4e66-9408-e08977e81d61"
	},
	{
			"title": "Oriental Bronze Sausages",
			"price": "38.00",
			"installment": 1,
			"image": "bis",
			"id": "4eae6acd-31a4-46c4-b340-fd17ecbf3c60"
	},
	{
			"title": "Generic Plastic Ball",
			"price": "84.00",
			"installment": 1,
			"image": "bis",
			"id": "cfe9d0b1-5ded-4c03-ac98-449483ff356c"
	},
	{
			"title": "Electronic Concrete Sausages",
			"price": "65.00",
			"installment": 1,
			"image": "bis",
			"id": "c3ad49bf-66e0-428e-8a56-b851bd3ee35d"
	},
	{
			"title": "Small Frozen Fish",
			"price": "4.00",
			"installment": 1,
			"image": "bis",
			"id": "9efd459b-61d9-4f4f-b52f-07d636c39978"
	},
	{
			"title": "Generic Plastic Ball",
			"price": "69.00",
			"installment": 1,
			"image": "bis",
			"id": "546d3a72-7fc3-4845-9fac-61745ab9b65e"
	},
	{
			"title": "Gorgeous Soft Shoes",
			"price": "21.00",
			"installment": 1,
			"image": "bis",
			"id": "750b3f56-f2d9-4222-acd5-1cc2fee04d32"
	},
	{
			"title": "Elegant Wooden Table",
			"price": "45.00",
			"installment": 1,
			"image": "bis",
			"id": "4a98abdd-a31e-4830-8998-f2a4725f3348"
	},
	{
			"title": "Tasty Frozen Gloves",
			"price": "16.00",
			"installment": 1,
			"image": "bis",
			"id": "d1dbfe68-73f2-473b-9e97-b011918686c6"
	},
	{
			"title": "Licensed Fresh Chicken",
			"price": "23.00",
			"installment": 1,
			"image": "bis",
			"id": "220fe551-33c5-4009-8ca1-107463ba1152"
	},
	{
			"title": "Handcrafted Bronze Soap",
			"price": "79.00",
			"installment": 1,
			"image": "bis",
			"id": "e6ab3020-d66e-4a0b-ab68-8102f0baa9ca"
	},
	{
			"title": "Modern Plastic Computer",
			"price": "15.00",
			"installment": 1,
			"image": "bis",
			"id": "0042a91a-c315-4912-a85c-504d7ba8fc6b"
	},
	{
			"title": "Electronic Steel Pants",
			"price": "43.00",
			"installment": 1,
			"image": "bis",
			"id": "45a25e0d-87d3-48cf-93a8-2ea359e33c73"
	},
	{
			"title": "Elegant Frozen Hat",
			"price": "99.00",
			"installment": 1,
			"image": "bis",
			"id": "306cf885-c3ee-43c0-a0ab-513564f87355"
	},
	{
			"title": "Licensed Soft Bacon",
			"price": "41.00",
			"installment": 1,
			"image": "bis",
			"id": "02ff76ae-0ab7-49cc-8d11-ad9e300074a7"
	},
	{
			"title": "Handcrafted Fresh Bacon",
			"price": "100.00",
			"installment": 1,
			"image": "bis",
			"id": "42b3b721-8751-4992-939f-c0f8e3c0b43f"
	},
	{
			"title": "Elegant Steel Bike",
			"price": "24.00",
			"installment": 1,
			"image": "bis",
			"id": "45c82331-dfda-46eb-a6b3-6cdd09dd22dc"
	},
	{
			"title": "Sleek Rubber Bike",
			"price": "69.00",
			"installment": 1,
			"image": "bis",
			"id": "d1257090-12b7-4f0d-9957-f87cdbc1c8a4"
	},
	{
			"title": "Handmade Wooden Towels",
			"price": "100.00",
			"installment": 1,
			"image": "bis",
			"id": "81a3b6e2-4915-4378-bf94-f10e6601b2df"
	},
	{
			"title": "Modern Steel Chair",
			"price": "44.00",
			"installment": 1,
			"image": "bis",
			"id": "677ea364-73f8-4a38-bfe0-f95164a1148f"
	},
	{
			"title": "Ergonomic Rubber Pants",
			"price": "66.00",
			"installment": 1,
			"image": "bis",
			"id": "4dad5969-fe0c-4902-8784-0ea2c4c08f99"
	},
	{
			"title": "Incredible Rubber Computer",
			"price": "49.00",
			"installment": 1,
			"image": "bis",
			"id": "bfa84113-a477-4955-993a-dbb1a9cdd47b"
	},
	{
			"title": "Electronic Fresh Cheese",
			"price": "61.00",
			"installment": 1,
			"image": "bis",
			"id": "067de317-0e5d-4c30-a58a-af55685b2430"
	},
	{
			"title": "Handmade Bronze Salad",
			"price": "77.00",
			"installment": 1,
			"image": "bis",
			"id": "e94ea9df-639f-44da-8cb4-ae854c45c1d1"
	},
	{
			"title": "Practical Plastic Gloves",
			"price": "5.00",
			"installment": 1,
			"image": "bis",
			"id": "a25cd6af-e2aa-4635-8bb2-6d468a08b984"
	},
	{
			"title": "Elegant Granite Chicken",
			"price": "30.00",
			"installment": 1,
			"image": "bis",
			"id": "a5a0fd88-a9a6-44e5-a75f-97c9359963a6"
	},
	{
			"title": "Gorgeous Concrete Pizza",
			"price": "10.00",
			"installment": 1,
			"image": "bis",
			"id": "161567fd-9eb9-4f51-ac89-3bfc411bef8b"
	},
	{
			"title": "Handcrafted Plastic Table",
			"price": "97.00",
			"installment": 1,
			"image": "bis",
			"id": "e92b5910-db07-4272-a4f2-5e6eb6f2ff16"
	},
	{
			"title": "Licensed Steel Hat",
			"price": "2.00",
			"installment": 1,
			"image": "bis",
			"id": "1c5c7915-76de-4785-bf9b-49964930b7b9"
	},
	{
			"title": "Ergonomic Plastic Car",
			"price": "75.00",
			"installment": 1,
			"image": "bis",
			"id": "42254a65-8b0c-4230-829e-9ce7df09d81b"
	},
	{
			"title": "Handmade Fresh Sausages",
			"price": "39.00",
			"installment": 1,
			"image": "bis",
			"id": "632bc9e5-fe2c-4f23-897f-9532c296ec3f"
	},
	{
			"title": "Gorgeous Soft Pizza",
			"price": "55.00",
			"installment": 1,
			"image": "bis",
			"id": "2a2448b0-394c-436d-b2a1-70aab92d7675"
	},
	{
			"title": "Handmade Rubber Pants",
			"price": "31.00",
			"installment": 1,
			"image": "bis",
			"id": "a8dc26d8-cacc-4bf0-95d6-3ce73fbb4676"
	},
	{
			"title": "Practical Concrete Car",
			"price": "31.00",
			"installment": 1,
			"image": "bis",
			"id": "73f0c2e6-2c9b-4e3b-a677-f0f965c717d0"
	},
	{
			"title": "Handcrafted Rubber Gloves",
			"price": "69.00",
			"installment": 1,
			"image": "bis",
			"id": "4df613d9-3390-4a89-a405-9c212802d195"
	},
	{
			"title": "Sleek Cotton Chips",
			"price": "82.00",
			"installment": 1,
			"image": "bis",
			"id": "2af1d84f-8749-4d7c-a1d1-59815ac11c18"
	},
	{
			"title": "Gorgeous Metal Salad",
			"price": "71.00",
			"installment": 1,
			"image": "bis",
			"id": "aaa3a7f7-35dd-4ae1-bcd6-78664c37238b"
	},
	{
			"title": "Awesome Steel Fish",
			"price": "64.00",
			"installment": 1,
			"image": "bis",
			"id": "a8054c0f-8561-438a-ae93-c0a7b52cc00c"
	},
	{
			"title": "Practical Rubber Soap",
			"price": "52.00",
			"installment": 1,
			"image": "bis",
			"id": "db88f82f-d0b5-488f-8b3d-3b9553fdf20a"
	},
	{
			"title": "Tasty Granite Soap",
			"price": "82.00",
			"installment": 1,
			"image": "bis",
			"id": "8a5677fa-ce5a-433e-bd72-f8b0a7ce336b"
	},
	{
			"title": "Incredible Concrete Chips",
			"price": "9.00",
			"installment": 1,
			"image": "bis",
			"id": "46bd8941-23e7-4846-93f0-eb40c0705a22"
	},
	{
			"title": "Unbranded Wooden Computer",
			"price": "35.00",
			"installment": 1,
			"image": "bis",
			"id": "f9c1d9f7-4ca8-4e43-9ab6-90edc5555c4f"
	},
	{
			"title": "Licensed Soft Bacon",
			"price": "85.00",
			"installment": 1,
			"image": "bis",
			"id": "f44cec57-1b5a-4853-8e54-8dbbeb918d3f"
	},
	{
			"title": "Bespoke Frozen Car",
			"price": "22.00",
			"installment": 1,
			"image": "bis",
			"id": "eb90a367-0699-4a12-93dd-14c51b725a73"
	},
	{
			"title": "Oriental Steel Pants",
			"price": "13.00",
			"installment": 1,
			"image": "bis",
			"id": "3680fa84-6b87-4a7d-80ee-251326e697bc"
	},
	{
			"title": "Tasty Fresh Towels",
			"price": "49.00",
			"installment": 1,
			"image": "bis",
			"id": "013d02c4-1136-48dc-bca3-4feea011e730"
	},
	{
			"title": "Ergonomic Steel Fish",
			"price": "28.00",
			"installment": 1,
			"image": "bis",
			"id": "3297d01b-f5ac-46f3-95ef-8c089741b4ed"
	},
	{
			"title": "Sleek Wooden Salad",
			"price": "29.00",
			"installment": 1,
			"image": "bis",
			"id": "187ce717-4124-4f56-b945-30c2a5b84bd7"
	},
	{
			"title": "Practical Granite Pants",
			"price": "96.00",
			"installment": 1,
			"image": "bis",
			"id": "8cf9cacd-04e8-4524-bbe0-77eb5daf2861"
	},
	{
			"title": "Small Wooden Tuna",
			"price": "55.00",
			"installment": 1,
			"image": "bis",
			"id": "3e70eebb-9ea0-4bac-911b-d46ce7d4a94c"
	},
	{
			"title": "Fantastic Wooden Mouse",
			"price": "26.00",
			"installment": 1,
			"image": "bis",
			"id": "877dcc2d-6635-4f57-9383-a37664b3b063"
	},
	{
			"title": "Luxurious Metal Chair",
			"price": "79.00",
			"installment": 1,
			"image": "bis",
			"id": "14df59d4-db4f-496d-873e-0263aee661dd"
	},
	{
			"title": "Handmade Wooden Ball",
			"price": "43.00",
			"installment": 1,
			"image": "bis",
			"id": "cc22c3e6-25d7-4587-bc06-aeca7f2e9f5a"
	},
	{
			"title": "Generic Wooden Sausages",
			"price": "99.00",
			"installment": 1,
			"image": "bis",
			"id": "73d30dd8-e408-4362-aad5-1ee25c5d8cff"
	},
	{
			"title": "Practical Bronze Chicken",
			"price": "71.00",
			"installment": 1,
			"image": "bis",
			"id": "0b3a0554-dde2-4eeb-92d7-d0479f9413a2"
	},
	{
			"title": "Sleek Plastic Shirt",
			"price": "20.00",
			"installment": 1,
			"image": "bis",
			"id": "0b5d3a82-0619-488f-b668-54bcf19c1d20"
	},
	{
			"title": "Small Plastic Gloves",
			"price": "55.00",
			"installment": 1,
			"image": "bis",
			"id": "7a340d0c-7b91-4437-b63f-6fb6ba8c3a09"
	},
	{
			"title": "Awesome Steel Chair",
			"price": "76.00",
			"installment": 1,
			"image": "bis",
			"id": "2dbb8533-aff2-43f6-a858-005bf2824b58"
	},
	{
			"title": "Incredible Fresh Sausages",
			"price": "79.00",
			"installment": 1,
			"image": "bis",
			"id": "f8f2ade1-c59f-4ee7-83bc-34898d7c4869"
	},
	{
			"title": "Ergonomic Cotton Keyboard",
			"price": "71.00",
			"installment": 1,
			"image": "bis",
			"id": "b9098578-b2e3-4987-ba37-46a4ccbd9875"
	},
	{
			"title": "Small Fresh Keyboard",
			"price": "76.00",
			"installment": 1,
			"image": "bis",
			"id": "b1057e13-7ab7-4119-8899-419b217b54ca"
	},
	{
			"title": "Small Frozen Pants",
			"price": "74.00",
			"installment": 1,
			"image": "bis",
			"id": "b74b1f63-4aa4-438a-bdf0-c1c6845043c7"
	},
	{
			"title": "Tasty Granite Sausages",
			"price": "12.00",
			"installment": 1,
			"image": "bis",
			"id": "0d13b032-3c4c-4a60-bda4-1e4c5991bd65"
	},
	{
			"title": "Luxurious Frozen Keyboard",
			"price": "86.00",
			"installment": 1,
			"image": "bis",
			"id": "b02e2fc2-4812-4eb4-aeab-65b770bcf37e"
	},
	{
			"title": "Tasty Concrete Salad",
			"price": "26.00",
			"installment": 1,
			"image": "bis",
			"id": "6f30c343-0efd-4a20-8c97-258b499712ba"
	},
	{
			"title": "Intelligent Fresh Keyboard",
			"price": "18.00",
			"installment": 1,
			"image": "bis",
			"id": "7f941b6d-6446-4d6c-a928-624bc70205a0"
	},
	{
			"title": "Ergonomic Soft Table",
			"price": "73.00",
			"installment": 1,
			"image": "bis",
			"id": "d2893ea2-80b3-4d8e-8286-9ac340ee1f27"
	},
	{
			"title": "Intelligent Metal Salad",
			"price": "8.00",
			"installment": 1,
			"image": "bis",
			"id": "0aaa355a-e915-4703-bd95-7ad2597849c8"
	},
	{
			"title": "Tasty Steel Pants",
			"price": "47.00",
			"installment": 1,
			"image": "bis",
			"id": "48fd4ef7-7ca6-4f8f-a5e1-6582e2b20bba"
	},
	{
			"title": "Intelligent Plastic Shirt",
			"price": "4.00",
			"installment": 1,
			"image": "bis",
			"id": "70e96b0e-c38a-4972-bc79-e1e29dd6e4de"
	},
	{
			"title": "Generic Frozen Towels",
			"price": "66.00",
			"installment": 1,
			"image": "bis",
			"id": "77b35353-e34d-4c30-a538-ab221f664e64"
	},
	{
			"title": "Licensed Plastic Shirt",
			"price": "85.00",
			"installment": 1,
			"image": "bis",
			"id": "19ebdd67-e667-4f71-99b1-33359b21af59"
	},
	{
			"title": "Refined Bronze Tuna",
			"price": "48.00",
			"installment": 1,
			"image": "bis",
			"id": "17bdf72d-bb7b-4af7-949a-b6203afcb7d1"
	},
	{
			"title": "Small Bronze Gloves",
			"price": "62.00",
			"installment": 1,
			"image": "bis",
			"id": "11e08c11-c660-4753-8f56-bbe70d4d4460"
	},
	{
			"title": "Sleek Cotton Chicken",
			"price": "67.00",
			"installment": 1,
			"image": "bis",
			"id": "4a6bbf26-6229-487a-8831-cb8fd28e6bd1"
	},
	{
			"title": "Rustic Cotton Chips",
			"price": "28.00",
			"installment": 1,
			"image": "bis",
			"id": "41722313-d255-47de-842f-d7dabae341ce"
	},
	{
			"title": "Elegant Steel Table",
			"price": "39.00",
			"installment": 1,
			"image": "bis",
			"id": "57cd8ba6-a359-4684-8001-17db6aeaa157"
	},
	{
			"title": "Sleek Wooden Keyboard",
			"price": "18.00",
			"installment": 1,
			"image": "bis",
			"id": "e6b277bd-2877-457a-ab76-70300ed4bb82"
	},
	{
			"title": "Fantastic Rubber Chicken",
			"price": "73.00",
			"installment": 1,
			"image": "bis",
			"id": "55668add-619a-410f-b61e-084542b48171"
	},
	{
			"title": "Incredible Steel Tuna",
			"price": "45.00",
			"installment": 1,
			"image": "bis",
			"id": "89b9cf3d-1c95-4e4e-8de8-2e9900975d8b"
	},
	{
			"title": "Oriental Cotton Soap",
			"price": "70.00",
			"installment": 1,
			"image": "bis",
			"id": "84826b7d-df6d-44dc-8436-4c45fef377d7"
	},
	{
			"title": "Tasty Steel Tuna",
			"price": "65.00",
			"installment": 1,
			"image": "bis",
			"id": "e072750f-3e0f-4fff-aa58-0d4227b4982a"
	},
	{
			"title": "Elegant Bronze Gloves",
			"price": "93.00",
			"installment": 1,
			"image": "bis",
			"id": "5a693f70-22cd-4019-8b16-491394c4df8f"
	},
	{
			"title": "Sleek Wooden Car",
			"price": "4.00",
			"installment": 1,
			"image": "bis",
			"id": "5b3f074c-6bc7-45d5-8623-da396d92de1c"
	},
	{
			"title": "Awesome Metal Tuna",
			"price": "5.00",
			"installment": 1,
			"image": "bis",
			"id": "f9a1301f-7329-425c-8fa8-7a8cb8761e7e"
	},
	{
			"title": "Sleek Wooden Pizza",
			"price": "56.00",
			"installment": 1,
			"image": "bis",
			"id": "168630f8-1f55-4e18-bf37-a9a16c86463e"
	},
	{
			"title": "Handmade Plastic Cheese",
			"price": "61.00",
			"installment": 1,
			"image": "bis",
			"id": "cfa4dbb9-f789-484b-a32f-4c4b71df097d"
	},
	{
			"title": "Rustic Concrete Sausages",
			"price": "47.00",
			"installment": 1,
			"image": "bis",
			"id": "368e4362-16cf-4998-a45d-faed8883f264"
	},
	{
			"title": "Generic Wooden Shirt",
			"price": "6.00",
			"installment": 1,
			"image": "bis",
			"id": "c84a3607-f2fb-49ea-b3c1-f14486815043"
	},
	{
			"title": "Handcrafted Concrete Car",
			"price": "3.00",
			"installment": 1,
			"image": "bis",
			"id": "6b0ffd6b-abac-40c3-a818-602fbf5d1650"
	},
	{
			"title": "Ergonomic Plastic Chips",
			"price": "72.00",
			"installment": 1,
			"image": "bis",
			"id": "7adfcb22-a6be-40f7-affe-52e9c66bbf5f"
	},
	{
			"title": "Generic Bronze Towels",
			"price": "83.00",
			"installment": 1,
			"image": "bis",
			"id": "ac58c11d-9ea6-44b8-930f-9d496bec6603"
	},
	{
			"title": "Bespoke Bronze Keyboard",
			"price": "15.00",
			"installment": 1,
			"image": "bis",
			"id": "ec7bcb89-c22a-463b-9f43-bf49375fe1a8"
	},
	{
			"title": "Oriental Soft Bacon",
			"price": "25.00",
			"installment": 1,
			"image": "bis",
			"id": "0c00af54-9708-4b62-8976-affd4341bf96"
	},
	{
			"title": "Intelligent Wooden Ball",
			"price": "89.00",
			"installment": 1,
			"image": "bis",
			"id": "deb33158-45fc-4308-bf9c-d3c523afee29"
	},
	{
			"title": "Practical Steel Salad",
			"price": "82.00",
			"installment": 1,
			"image": "bis",
			"id": "2d543055-f812-4f53-89e7-13f9e74118f9"
	},
	{
			"title": "Small Soft Shoes",
			"price": "73.00",
			"installment": 1,
			"image": "bis",
			"id": "f71412ad-20fa-4708-9c67-76b16cbd3e31"
	},
	{
			"title": "Small Steel Chicken",
			"price": "29.00",
			"installment": 1,
			"image": "bis",
			"id": "e9ba2fb4-14ff-43c2-9fc4-0cf4fa52b6b0"
	},
	{
			"title": "Gorgeous Concrete Computer",
			"price": "75.00",
			"installment": 1,
			"image": "bis",
			"id": "12330701-1e5c-4c90-bda0-a8d839d28cea"
	},
	{
			"title": "Sleek Concrete Tuna",
			"price": "74.00",
			"installment": 1,
			"image": "bis",
			"id": "9f86c23c-97d1-4347-ad00-6cfb3b2b7988"
	},
	{
			"title": "Oriental Metal Fish",
			"price": "87.00",
			"installment": 1,
			"image": "bis",
			"id": "71f12051-0bd2-4c96-8437-4ee0727269d4"
	},
	{
			"title": "Licensed Fresh Shoes",
			"price": "14.00",
			"installment": 1,
			"image": "bis",
			"id": "37eb9d69-eccd-4f77-8989-809ad8fb708e"
	},
	{
			"title": "Luxurious Granite Cheese",
			"price": "83.00",
			"installment": 1,
			"image": "bis",
			"id": "f6b1ff12-aff0-4b8a-b74c-aa9c0fd39ad0"
	},
	{
			"title": "Unbranded Fresh Bacon",
			"price": "50.00",
			"installment": 1,
			"image": "bis",
			"id": "2c6a0fc0-498d-4d16-8081-242553dce0ec"
	},
	{
			"title": "Refined Cotton Mouse",
			"price": "72.00",
			"installment": 1,
			"image": "bis",
			"id": "b1b5a386-1b45-430e-bd32-4385fcfa299a"
	},
	{
			"title": "Intelligent Cotton Cheese",
			"price": "10.00",
			"installment": 1,
			"image": "bis",
			"id": "e8c730d0-1cda-4dd8-80b8-642c11a8186b"
	},
	{
			"title": "Recycled Soft Salad",
			"price": "85.00",
			"installment": 1,
			"image": "bis",
			"id": "25d43f59-2c15-48ba-9d2e-39d2c03bd154"
	},
	{
			"title": "Elegant Cotton Shirt",
			"price": "80.00",
			"installment": 1,
			"image": "bis",
			"id": "31441c2a-ee87-4167-8208-230793d07732"
	},
	{
			"title": "Refined Metal Hat",
			"price": "97.00",
			"installment": 1,
			"image": "bis",
			"id": "e0bda20a-95e9-4ca1-99a6-6bdc36c43f04"
	},
	{
			"title": "Rustic Concrete Tuna",
			"price": "68.00",
			"installment": 1,
			"image": "bis",
			"id": "9f65ec21-7396-4eb4-8546-5fe2dd46741a"
	},
	{
			"title": "Oriental Bronze Computer",
			"price": "95.00",
			"installment": 1,
			"image": "bis",
			"id": "6514c4e6-5cdb-46cc-9849-ccab90b2df29"
	},
	{
			"title": "Modern Soft Pizza",
			"price": "50.00",
			"installment": 1,
			"image": "bis",
			"id": "33871245-fdc0-49be-9061-1c90f6d097e5"
	},
	{
			"title": "Bespoke Plastic Gloves",
			"price": "51.00",
			"installment": 1,
			"image": "bis",
			"id": "269935e1-5d20-49d7-a9fd-0629c2ac4512"
	},
	{
			"title": "Rustic Metal Tuna",
			"price": "36.00",
			"installment": 1,
			"image": "bis",
			"id": "5d36ab42-fd68-4344-8627-0041623ea58d"
	},
	{
			"title": "Fantastic Cotton Ball",
			"price": "53.00",
			"installment": 1,
			"image": "bis",
			"id": "2b1c57f6-0535-4224-bd19-e2b2ca617ca4"
	},
	{
			"title": "Refined Frozen Towels",
			"price": "5.00",
			"installment": 1,
			"image": "bis",
			"id": "e7e0a2f7-0c90-4714-a38f-5bcfdf5a2963"
	},
	{
			"title": "Small Metal Car",
			"price": "18.00",
			"installment": 1,
			"image": "bis",
			"id": "22e54f32-159d-4dea-91ea-fc3285679651"
	},
	{
			"title": "Sleek Cotton Ball",
			"price": "83.00",
			"installment": 1,
			"image": "bis",
			"id": "9b10d0c4-284f-462d-b720-9879985d9e35"
	},
	{
			"title": "Ergonomic Metal Cheese",
			"price": "51.00",
			"installment": 1,
			"image": "bis",
			"id": "231749ff-9d80-4a79-b924-94a789c570bd"
	},
	{
			"title": "Generic Rubber Bacon",
			"price": "96.00",
			"installment": 1,
			"image": "bis",
			"id": "c4cdc797-69d7-4920-b1f1-ac4bb9efa4e6"
	},
	{
			"title": "Bespoke Granite Keyboard",
			"price": "44.00",
			"installment": 1,
			"image": "bis",
			"id": "5b126659-cc2d-4764-870a-9760b6dc4f35"
	},
	{
			"title": "Oriental Concrete Fish",
			"price": "69.00",
			"installment": 1,
			"image": "bis",
			"id": "bb5f5ace-6ea3-4407-8bc9-31f7f25aff81"
	},
	{
			"title": "Luxurious Steel Soap",
			"price": "15.00",
			"installment": 1,
			"image": "bis",
			"id": "2f865c4c-896e-44ff-9f1c-f5ac16c63ed5"
	},
	{
			"title": "Unbranded Frozen Fish",
			"price": "23.00",
			"installment": 1,
			"image": "bis",
			"id": "8db06e24-da5a-464e-8d5d-9f54e79321ca"
	},
	{
			"title": "Ergonomic Rubber Chair",
			"price": "53.00",
			"installment": 1,
			"image": "bis",
			"id": "adeea9b0-cd0e-4c9e-8086-de698c4ff673"
	},
	{
			"title": "Generic Metal Chips",
			"price": "1.00",
			"installment": 1,
			"image": "bis",
			"id": "5c04837d-0bae-40ae-9bc7-4bcdf4724e7f"
	},
	{
			"title": "Awesome Frozen Keyboard",
			"price": "95.00",
			"installment": 1,
			"image": "bis",
			"id": "345aa6c1-03f6-4bbb-881c-25e1c559b725"
	},
	{
			"title": "Recycled Plastic Soap",
			"price": "20.00",
			"installment": 1,
			"image": "bis",
			"id": "5a2dfb58-14be-4925-8885-6fa2f918fe71"
	},
	{
			"title": "Bespoke Rubber Towels",
			"price": "62.00",
			"installment": 1,
			"image": "bis",
			"id": "dfb87e3d-27c5-406c-b328-d35308265770"
	},
	{
			"title": "Incredible Bronze Bacon",
			"price": "51.00",
			"installment": 1,
			"image": "bis",
			"id": "ae352b1e-dd71-47f2-9913-fe646ffc4190"
	},
	{
			"title": "Awesome Fresh Tuna",
			"price": "51.00",
			"installment": 1,
			"image": "bis",
			"id": "f20f6d3d-0432-430b-8e93-2fadc7c42f79"
	},
	{
			"title": "Electronic Steel Computer",
			"price": "40.00",
			"installment": 1,
			"image": "bis",
			"id": "9614090a-300c-4eb7-bb48-b38ffaa495f1"
	},
	{
			"title": "Handcrafted Fresh Chicken",
			"price": "69.00",
			"installment": 1,
			"image": "bis",
			"id": "9ed4ffd5-6214-463e-b2ab-fa427bac5a09"
	},
	{
			"title": "Bespoke Frozen Sausages",
			"price": "49.00",
			"installment": 1,
			"image": "bis",
			"id": "9f8a08c6-a85e-4cb7-be76-4932919d3061"
	},
	{
			"title": "Unbranded Fresh Mouse",
			"price": "8.00",
			"installment": 1,
			"image": "bis",
			"id": "75964518-2c07-4144-91d1-638947030633"
	},
	{
			"title": "Unbranded Bronze Bike",
			"price": "15.00",
			"installment": 1,
			"image": "bis",
			"id": "9e026f93-b707-4af4-8fed-b4aabda35bb2"
	}
  ]
}